{"assets/1.jpeg":["assets/1.jpeg"],"assets/2.jpeg":["assets/2.jpeg"],"assets/3.jpeg":["assets/3.jpeg"],"assets/4.jpeg":["assets/4.jpeg"],"assets/5.jpeg":["assets/5.jpeg"],"assets/banner_post.png":["assets/banner_post.png"],"assets/mimir_logo.png":["assets/mimir_logo.png"],"assets/mimir_logo_round.png":["assets/mimir_logo_round.png"],"assets/mimir_text_grey.png":["assets/mimir_text_grey.png"],"assets/mimir_text_white.png":["assets/mimir_text_white.png"],"assets/sample-feed.png":["assets/sample-feed.png"],"assets/user.svg":["assets/user.svg"],"fonts/Lora-Regular.ttf":["fonts/Lora-Regular.ttf"],"fonts/Mimir.ttf":["fonts/Mimir.ttf"],"fonts/Poppins-Light.ttf":["fonts/Poppins-Light.ttf"],"fonts/Poppins-Medium.ttf":["fonts/Poppins-Medium.ttf"],"packages/cupertino_icons/assets/CupertinoIcons.ttf":["packages/cupertino_icons/assets/CupertinoIcons.ttf"]}